libname/__init__.py
libname/mustafapy.py
mustafapy-0.0.14.dist-info/METADATA
mustafapy-0.0.14.dist-info/WHEEL
mustafapy-0.0.14.dist-info/top_level.txt
mustafapy-0.0.14.dist-info/RECORD
