Metadata-Version: 2.1
Name: mustafapy
Version: 0.0.14
Summary: GridSearchCV hyperparameters generation
Home-page: UNKNOWN
Author: mustafasa (Mustafa Al Hamad)
Author-email: <mustafa.alhamad.sa@gmail.com>
License: UNKNOWN
Keywords: python,sklearn,gridsearch,machine learning,automation,sockets
Platform: UNKNOWN
Classifier: Development Status :: 1 - Planning
Classifier: Intended Audience :: Developers
Classifier: Programming Language :: Python :: 3
Classifier: Operating System :: Unix
Classifier: Operating System :: MacOS :: MacOS X
Classifier: Operating System :: Microsoft :: Windows
Requires-Dist: sklearn
Requires-Dist: imblearn
Requires-Dist: pandas
